python_sumo-0.3.0.data/data/etc/config.yml
sumo/__init__.py
sumo/__main__.py
sumo/command_line.py
sumo/constants.py
sumo/network.py
sumo/run.py
sumo/utils.py
sumo/modes/__init__.py
sumo/modes/mode.py
sumo/modes/evaluate/__init__.py
sumo/modes/evaluate/evaluate.py
sumo/modes/interpret/__init__.py
sumo/modes/interpret/interpret.py
sumo/modes/prepare/__init__.py
sumo/modes/prepare/prepare.py
sumo/modes/prepare/similarity.py
sumo/modes/run/__init__.py
sumo/modes/run/run.py
sumo/modes/run/solver.py
sumo/modes/run/utils.py
sumo/modes/run/solvers/__init__.py
sumo/modes/run/solvers/supervised_sumo.py
sumo/modes/run/solvers/unsupervised_sumo.py
python_sumo-0.3.0.dist-info/AUTHORS.rst
python_sumo-0.3.0.dist-info/LICENSE
python_sumo-0.3.0.dist-info/METADATA
python_sumo-0.3.0.dist-info/WHEEL
python_sumo-0.3.0.dist-info/entry_points.txt
python_sumo-0.3.0.dist-info/top_level.txt
python_sumo-0.3.0.dist-info/RECORD
