Metadata-Version: 2.1
Name: python-sumo
Version: 0.3.0
Summary: **sumo** is a command-line tool to identify molecular subtypes in multi-omics datasets. It implements a novel nonnegative matrix factorization (NMF) algorithm to identify groups of samples that share molecular signatures, and provides additional modules to evaluate such assignments and identify features that drive the classification.
Home-page: https://github.com/ratan-lab/sumo
Author: Karolina Sienkiewicz
Author-email: sienkiewicz2k@gmail.com
License: UNKNOWN
Platform: UNKNOWN
Classifier: License :: OSI Approved :: MIT License
Classifier: Natural Language :: English
Classifier: Programming Language :: Python :: 3
Classifier: Programming Language :: Python :: 3.6
Classifier: Programming Language :: Python :: 3.7
Requires-Dist: hyperopt
Requires-Dist: lightgbm
Requires-Dist: matplotlib
Requires-Dist: numba
Requires-Dist: numpy (>=1.18.5)
Requires-Dist: pandas
Requires-Dist: scikit-learn (>=0.22)
Requires-Dist: scipy
Requires-Dist: seaborn
Requires-Dist: shap
